operator_core/__init__.py
bfiola_operator_core-3.0.1.dist-info/METADATA
bfiola_operator_core-3.0.1.dist-info/WHEEL
bfiola_operator_core-3.0.1.dist-info/top_level.txt
bfiola_operator_core-3.0.1.dist-info/RECORD
