Metadata-Version: 2.1
Name: bfiola-operator-core
Version: 3.0.1
Requires-Dist: fastapi
Requires-Dist: kopf
Requires-Dist: lightkube
Requires-Dist: lightkube-models
Requires-Dist: pydantic
Requires-Dist: uvicorn
Provides-Extra: dev
Requires-Dist: black ; extra == 'dev'
Requires-Dist: build ; extra == 'dev'
Requires-Dist: twine ; extra == 'dev'
